mojang/__init__.py
mojang/_version.py
mojang/exceptions.py
mojang/api/__init__.py
mojang/api/base.py
mojang/api/helpers.py
mojang/api/models.py
mojang/api/session.py
mojang/api/structures.py
mojang/api/urls.py
mojang/api/auth/__init__.py
mojang/api/auth/microsoft.py
mojang/api/auth/models.py
mojang/minecraft/__init__.py
mojang/minecraft/launchermeta.py
mojang/minecraft/query/__init__.py
mojang/minecraft/query/_structures.py
mojang/minecraft/query/packets.py
mojang/minecraft/rcon/__init__.py
mojang/minecraft/rcon/packets.py
mojang/minecraft/slp/__init__.py
mojang/minecraft/slp/_structures.py
mojang/minecraft/slp/post_netty/__init__.py
mojang/minecraft/slp/post_netty/packets.py
mojang/minecraft/slp/post_netty/types.py
mojang/minecraft/slp/pre_netty/__init__.py
pymojang-2.0.6.dist-info/LICENSE
pymojang-2.0.6.dist-info/METADATA
pymojang-2.0.6.dist-info/WHEEL
pymojang-2.0.6.dist-info/top_level.txt
pymojang-2.0.6.dist-info/RECORD
