Metadata-Version: 2.1
Name: pymojang
Version: 2.0.6
Summary: It's a full wrapper arround the Mojang API and Mojang Authentication API
Author-email: Lucino772 <lucapalmi772@gmail.com>
License: MIT
Project-URL: Homepage, https://github.com/Lucino772/pymojang
Project-URL: Documentation, https://lucino772.github.io/pymojang/
Keywords: minecraft,mojang,python3
Classifier: License :: OSI Approved :: MIT License
Classifier: Operating System :: OS Independent
Classifier: Programming Language :: Python :: 3.7
Classifier: Programming Language :: Python :: 3.8
Classifier: Programming Language :: Python :: 3.9
License-File: LICENSE
Requires-Dist: requests
Requires-Dist: validators
Requires-Dist: pyjwt[crypto]
Requires-Dist: msal
